unq/__init__.py
unq/models/__init__.py
unq/models/_future_function_call.py
unq/models/repetition_interval.py
unq/services/__init__.py
unq/services/_context_managed_rate_limiter.py
unq/services/rate_limiter.py
unq/services/abstract/__init__.py
unq/services/abstract/_abstract_rate_limiter.py
unq/services/abstract/_abstract_submittable.py
unq-1.0.1.dist-info/METADATA
unq-1.0.1.dist-info/WHEEL
unq-1.0.1.dist-info/licenses/LICENSE
unq-1.0.1.dist-info/RECORD
